main.py
setup.py
uus.egg-info/PKG-INFO
uus.egg-info/SOURCES.txt
uus.egg-info/dependency_links.txt
uus.egg-info/requires.txt
uus.egg-info/top_level.txt